{"BEh9s+QTW3gK7mPXofAS8g==":"sin%20t%C3%ADtulo-1316x1364.png","8ur8gXRpTPTv4bgdRHcQ9g==":"sin%20t%C3%ADtulo-1316x1364.png","d+ePCNcf0Dvm3SUFYTiZag==":"protesis-ergotec-tec-1280x960.png","iEpqUMstwD3hVE7PO/I7hw==":"diabetes-290x175.jpeg","dWehiZfTIYs1+nosbA0GIA==":"inge_biomedica_c-300x214.png","/I6G6CGT3skhRY5819zNIQ==":"diabetes-1-290x175.jpeg","Gdv93rxYymBfWCo6cbgJLw==":"diabetes-2-290x175.jpeg","LuJt12JGmMIDbRsRnPoyTQ==":"imagen1-815x737.png","rbwwcpMh+QKLxnQ6hH4DCw==":"imagen2-328x485.png","Wp4tBbmQoFFRtLkyYKdjfg==":"diabetes-1-600x375.jpeg","LEQgJU+fDWXcRhTRP1jrWw==":"diabetes-1-600x375.jpg","8J2xWrre5qw142lyVeSM8g==":"diabetes-2-600x375.jpeg","DAuiKtsUq+X+/sd4JULjTg==":"1510683652_139970_1510684260_noticia_normal-770x453.jpg","XyM4t93vkVndmUnL+xbKMA==":"1510683652_139970_1510684260_noticia_normal-770x453.jpeg","4/Xm1s6+A3fIrZTCeJSXSw==":"imagen3-686x697.png","T09AbAdVZU/AT4lPfY3dvg==":"7n7eqc_v_400x400-197x197.png","YT8cpFkCZz2sLMHO81pY9A==":"imagen4-424x477.png","OjqdMId6r18aigc9ktM/Ag==":"imagen5-327x137.png","9Pqe4CKYKXtprZRQeJNM0Q==":"imagen6-304x216.png","4MU8ffp10ToO0OVOwvMAIQ==":"pastilla-diabetes-676x376.jpeg","rz6OwPaCKc2iaa3MhNfY+w==":"mapa-de-valor-632x624.png","5HBVrjrHnhFkpa7LPRZXkg==":"1534351691_997591_1534352892_noticia_normal-980x652.jpg","+nnVQg1Ok0cAjJFJQnCTjg==":"inge-biomedica-c-1-300x214.png","3YTfx0SllolfLscO/s+JDw==":"logos-956x281.jpeg","COMiPb4A1jUNPTXMe6Qd0g==":"descarga-275x183.png","GJ4GKqH18CFbc6Gscfqo0g==":"descarga%20(1)-281x180.png","8qZhAQQTiosmDqYYQ5jhAQ==":"images%20(10)-300x168.jpg","nu3jyh7SdMIs4kaDDQBSRA==":"matriz-564x657.png","pNEwv5sKSt2MhysUKH5zEA==":"images%20(11)-226x223.jpg","wuNadTj0oLAXdMrr1N/49w==":"matriss%20bonita-799x1248.png","UAc7kepzJPkrSn4uqTRvmw==":"background4-1.jpg","6C27zJja8QQ6CfA7363tNA==":"patente%201-1368x1936.png","B/wQzKx38nNodQQXVSa4Sw==":"patente%202-1368x1934.png","vqGtFfs6njsoyCmDcDX+4A==":"pantente%203-1368x1936.png","NpT73peapy7fGqSVl/Krtw==":"patente%204-1368x1934.png","7EtTen3KjGpT7pDSgGWpJQ==":"patente%205-1368x1936.png","Zvx7D/hkeZyGsyvzD3Ki9A==":"sin%20t%C3%ADtulo-594x291.png","zum7zEmom68HzDrCWmFyeg==":"ronald-240x320.jpg","n//Yre4XFbsiAT4Cs9Yd+w==":"ronald-240x320.jpeg","yeFG3Vi6OBAMnP1IEXqBvg==":"jamila-240x320.jpeg","tCn7u23hX1tqxGAFUPhGOg==":"alejando-240x320.jpeg","VqKSKE8MAnP2HShpLkxsvQ==":"haru-240x320.jpeg","MoFnDSVwZ+Kptd//K/6vtg==":"111-343x224.png","ECxUORuvvPVvTEFLC59ZXA==":"22222-323x228.png","H2WwzWULuOp0rHenfso9rQ==":"333333-331x190.png","XUqvv2XMP/iAncOhZq6kQw==":"4444-304x192.png"}